create_brandon/__init__.py
create_brandon/create_brandon.py
create_brandon/scripts/__init__.py
create_brandon/scripts/helper_functions.py
create_brandon_brandonseverin-0.0.1.dist-info/LICENSE
create_brandon_brandonseverin-0.0.1.dist-info/METADATA
create_brandon_brandonseverin-0.0.1.dist-info/WHEEL
create_brandon_brandonseverin-0.0.1.dist-info/entry_points.txt
create_brandon_brandonseverin-0.0.1.dist-info/top_level.txt
create_brandon_brandonseverin-0.0.1.dist-info/RECORD
