Metadata-Version: 2.1
Name: create-brandon-brandonseverin
Version: 0.0.1
Summary: A small package to create experimental notebooks and directories
Home-page: https://github.com/brandonseverin/create_brandon_project
Author: Brandon Severin
Author-email: hi@brandonseverin.com
License: UNKNOWN
Project-URL: Bug Tracker, https://github.com/brandonseverin/create_brandon_project/issues
Platform: UNKNOWN
Classifier: Programming Language :: Python :: 3
Classifier: License :: OSI Approved :: MIT License
Classifier: Operating System :: OS Independent
Requires-Python: >=3.6
License-File: LICENSE
Requires-Dist: nbformat
Provides-Extra: dev
Requires-Dist: pytest (==6.2.5) ; extra == 'dev'
